setup.py
ikl_dsnd_probability/Binomialdistribution.py
ikl_dsnd_probability/Gaussiandistribution.py
ikl_dsnd_probability/Generaldistribution.py
ikl_dsnd_probability/__init__.py
ikl_dsnd_probability.egg-info/PKG-INFO
ikl_dsnd_probability.egg-info/SOURCES.txt
ikl_dsnd_probability.egg-info/dependency_links.txt
ikl_dsnd_probability.egg-info/not-zip-safe
ikl_dsnd_probability.egg-info/top_level.txt