Metadata-Version: 2.1
Name: ikl_dsnd_probability
Version: 0.1
Summary: Gaussian and Binomial distributions
